[
  {
    "ContainingType": "NlogDemo.Controllers.WeatherForecastController",
    "Method": "Get",
    "RelativePath": "WeatherForecast",
    "HttpMethod": "GET",
    "IsController": true,
    "Order": 0,
    "Parameters": [],
    "ReturnTypes": [],
    "EndpointName": "GetWeatherForecast"
  },
  {
    "ContainingType": "NlogDemo.Controllers.WeatherForecastController",
    "Method": "Hello",
    "RelativePath": "WeatherForecast",
    "HttpMethod": "POST",
    "IsController": true,
    "Order": 0,
    "Parameters": [
      {
        "Name": "name",
        "Type": "System.String",
        "IsRequired": true
      }
    ],
    "ReturnTypes": [],
    "EndpointName": "Hello"
  }
]